finalse_sdk/Amount.py
finalse_sdk/AmountCurrency.py
finalse_sdk/Attempt.py
finalse_sdk/AttemptParentType.py
finalse_sdk/AttemptService.py
finalse_sdk/AttemptStatus.py
finalse_sdk/AttemptValidation.py
finalse_sdk/Auth.py
finalse_sdk/AuthAccess.py
finalse_sdk/AuthAccessPermission.py
finalse_sdk/AuthAccessPermissionSimpleName.py
finalse_sdk/AuthAccessPermissionSimpleNameForm.py
finalse_sdk/AuthAccessService.py
finalse_sdk/Balance.py
finalse_sdk/BalanceType.py
finalse_sdk/Cancelled.py
finalse_sdk/Country.py
finalse_sdk/Creator.py
finalse_sdk/Dc.py
finalse_sdk/Deposit.py
finalse_sdk/DepositService.py
finalse_sdk/DepositStatus.py
finalse_sdk/Destination.py
finalse_sdk/Duration.py
finalse_sdk/DurationPart.py
finalse_sdk/Expire.py
finalse_sdk/FPayClient.py
finalse_sdk/Fees.py
finalse_sdk/FeesPayer.py
finalse_sdk/FeesPayerForm.py
finalse_sdk/FeesValue.py
finalse_sdk/FundRequest.py
finalse_sdk/FundRequestService.py
finalse_sdk/FundRequestStatus.py
finalse_sdk/H1.py
finalse_sdk/H1Descriptor.py
finalse_sdk/Http.py
finalse_sdk/HttpCallError.py
finalse_sdk/Iso3166CountryCode.py
finalse_sdk/LightAttempt.py
finalse_sdk/ListForm.py
finalse_sdk/LocalizedText.py
finalse_sdk/LocalizedVariableText.py
finalse_sdk/Man.py
finalse_sdk/Mars.py
finalse_sdk/MfaProcess.py
finalse_sdk/MfaProcessConfirm.py
finalse_sdk/MoneyAccount.py
finalse_sdk/MoneyAccountIdentifier.py
finalse_sdk/MoneyAccountIdentifierType.py
finalse_sdk/MoneyAccountProvider.py
finalse_sdk/OnCompletedCall.py
finalse_sdk/OnFundRequestCompleted.py
finalse_sdk/OnQuasiTransferCompleted.py
finalse_sdk/OnTransferCompleted.py
finalse_sdk/Otp.py
finalse_sdk/OtpAction.py
finalse_sdk/OtpChannel.py
finalse_sdk/Page.py
finalse_sdk/Pagination.py
finalse_sdk/Pocket.py
finalse_sdk/PurchaseLabel.py
finalse_sdk/QrCode.py
finalse_sdk/QuasiTransfer.py
finalse_sdk/QuasiTransferService.py
finalse_sdk/QuasiTransferStatus.py
finalse_sdk/Request.py
finalse_sdk/RestCollection.py
finalse_sdk/Sdk.py
finalse_sdk/SecurePay.py
finalse_sdk-1.0.3.dist-info/LICENSE
finalse_sdk-1.0.3.dist-info/METADATA
finalse_sdk-1.0.3.dist-info/WHEEL
finalse_sdk-1.0.3.dist-info/top_level.txt
finalse_sdk-1.0.3.dist-info/RECORD
