Metadata-Version: 2.1
Name: finalse-sdk
Version: 1.0.3
Summary: Sdk to access Finalse Cloud platform in Python based environment
Home-page: https://github.com/finalse/sdk-python
Author: Finalse Cloud Services
Author-email: opensource@finalse.com
Classifier: Programming Language :: Python :: 3
Classifier: License :: OSI Approved :: Apache Software License
Classifier: Operating System :: OS Independent
Requires-Python: >=3.5
License-File: LICENSE
Requires-Dist: requests
